hiveadb/__init__.py
hiveadb/functions.py
hiveadb/governance.py
hiveadb/py.typed
hivecore/__init__.py
hivecore/constant.py
hivecore/decorator.py
hivecore/eda.py
hivecore/exceptions.py
hivecore/functions.py
hivecore/patterns.py
hivecore/preprocess.py
hivecore/py.typed
hivesignal/__init__.py
hivesignal/analysis.py
hivesignal/eda.py
hivesignal/io.py
hivesignal/py.typed
hivesignal/transform.py
hivecode-0.0.0.8.36.dist-info/LICENSE
hivecode-0.0.0.8.36.dist-info/METADATA
hivecode-0.0.0.8.36.dist-info/WHEEL
hivecode-0.0.0.8.36.dist-info/top_level.txt
hivecode-0.0.0.8.36.dist-info/RECORD
