Metadata-Version: 2.1
Name: hivecode
Version: 0.0.0.8.36
Summary: Hivecode is a versatile and comprehensive Python library, with a focus on efficiency and reusability, Hivecode empowers developers and data enthusiasts alike to streamline their projects.
Author: Juan Manuel Mejía Botero
Author-email: Juan Manuel Mejía Botero <juanmam941025@gmail.com>, Sebastian López Valencia <sebaslv12@hotmail.com>
Project-URL: Homepage, https://github.com/Juanmam/hivecode
Project-URL: Documentation, https://hivecode.readthedocs.io/en/latest/
Platform: unix
Platform: linux
Platform: osx
Platform: cygwin
Platform: win32
Classifier: Programming Language :: Python :: 3.10
Classifier: Programming Language :: Python :: 3.11
Requires-Python: >=3.8.0
License-File: LICENSE
Requires-Dist: paramiko ==2.11.0
Requires-Dist: scp ==0.14.4
Requires-Dist: scikit-learn ==1.1.3
Requires-Dist: azure-cosmos ==4.3.0
Requires-Dist: openpyxl ==3.0.10
Requires-Dist: tqdm ==4.65.0
Requires-Dist: scipy ==1.10.0
Requires-Dist: matplotlib ==3.7.2
Requires-Dist: numpy ==1.25.0
Requires-Dist: pandas ==2.0.3
Requires-Dist: seaborn ==0.11.1
Requires-Dist: category-encoders ==2.6.1
Requires-Dist: polars ==0.18.7
Requires-Dist: databricks-api ==0.9.0
Provides-Extra: dev
Requires-Dist: build ; extra == 'dev'
Requires-Dist: twine ; extra == 'dev'
Requires-Dist: Sphinx ; extra == 'dev'
Provides-Extra: testing
Requires-Dist: pytest >=6.0 ; extra == 'testing'
Requires-Dist: pytest-cov >=2.0 ; extra == 'testing'
Requires-Dist: mypy >=0.910 ; extra == 'testing'
Requires-Dist: flake8 >=3.9 ; extra == 'testing'
Requires-Dist: tox >=3.24 ; extra == 'testing'
